sbom2csv/__init__.py
sbom2csv/generate.py
sbom2csv/generator.py
sbom2csv/version.py
sbom2csv-1.0.2.dist-info/LICENSE
sbom2csv-1.0.2.dist-info/METADATA
sbom2csv-1.0.2.dist-info/WHEEL
sbom2csv-1.0.2.dist-info/entry_points.txt
sbom2csv-1.0.2.dist-info/top_level.txt
sbom2csv-1.0.2.dist-info/RECORD
