Metadata-Version: 2.1
Name: sbom2csv
Version: 1.0.2
Summary: Transform SBOM contents into a formatted csv file.
Home-page: https://github.com/yuanzhou3118/sbom2csv
Author: Yuan Zhou
Author-email: zhouyuan3118@gmail.com
License: LICENSE
License-File: LICENSE
